LICENSE
MANIFEST.in
README.rst
setup.py
sphinxcontrib_yaml.py
sphinxcontrib_yaml.egg-info/PKG-INFO
sphinxcontrib_yaml.egg-info/SOURCES.txt
sphinxcontrib_yaml.egg-info/dependency_links.txt
sphinxcontrib_yaml.egg-info/requires.txt
sphinxcontrib_yaml.egg-info/top_level.txt