Metadata-Version: 1.1
Name: sphinxcontrib-yaml
Version: 1.0.0
Summary: Sphinx autodoc extension to generate docs from YAML comments
Home-page: https://github.com/Rayvenden/sphinxcontrib-yaml
Author: Jakub Pieńkowski
Author-email: jakski@sealcode.org
License: MIT
Platform: any
Classifier: Development Status :: 3 - Alpha
Classifier: Framework :: Sphinx :: Extension
Classifier: Intended Audience :: System Administrators
Classifier: License :: OSI Approved :: MIT License
Classifier: Topic :: Documentation
